Pipfile
Pipfile.lock
README.md
pyproject.toml
setup.py
test.sh
ff_client/__init__.py
ff_client/ff_client.py
ff_client/ff_config.py
ff_client/ff_request.py
ff_client/udp_packet.py
ff_client.egg-info/PKG-INFO
ff_client.egg-info/SOURCES.txt
ff_client.egg-info/dependency_links.txt
ff_client.egg-info/requires.txt
ff_client.egg-info/top_level.txt
tests/__init__.py
tests/test_encrypted_single_packet.py
tests/test_ff_client.py
tests/test_multi_packet.py
tests/test_single_packet.py