Metadata-Version: 2.1
Name: ff-client
Version: 1.0.0a20200425021050
Summary: Client library for ff-proxy
Home-page: https://github.com/TimeToogo/ff-proxy
Author: Elliot Levin
Author-email: elliotlevin@hotmail.com
License: UNKNOWN
Platform: UNKNOWN
Classifier: Programming Language :: Python :: 3
Classifier: License :: OSI Approved :: MIT License
Classifier: Operating System :: OS Independent
Requires-Python: >=3.6
